{
  "_readme": "이 파일을 직접 수정하거나, admin.html에서 링크를 입력 후 '내보내기 → JSON 다운로드'로 덮어쓰세요.",
  "_version": "1.0",

  "rs-1-2a": { "trackUrl": "", "videoUrl": "", "planUrl": "" },
  "rs-1-2b": { "trackUrl": "", "videoUrl": "", "planUrl": "" },
  "rsv-1-2a": { "trackUrl": "", "videoUrl": "", "planUrl": "" },
  "rsp-m-1-2": { "trackUrl": "", "videoUrl": "", "planUrl": "" },
  "rs-1-3a": { "trackUrl": "", "videoUrl": "", "planUrl": "" },
  "rs-1-3b": { "trackUrl": "", "videoUrl": "", "planUrl": "" },
  "rsv-1-3a": { "trackUrl": "", "videoUrl": "", "planUrl": "" },
  "rsp-m-1-3": { "trackUrl": "", "videoUrl": "", "planUrl": "" },
  "rs-1-4a": { "trackUrl": "", "videoUrl": "", "planUrl": "" },
  "rs-1-4b": { "trackUrl": "", "videoUrl": "", "planUrl": "" },
  "rsv-1-4a": { "trackUrl": "", "videoUrl": "", "planUrl": "" },
  "rsp-m-1-4": { "trackUrl": "", "videoUrl": "", "planUrl": "" },
  "rs-1-5a": { "trackUrl": "", "videoUrl": "", "planUrl": "" },
  "rs-1-5b": { "trackUrl": "", "videoUrl": "", "planUrl": "" },
  "rsp-m-1-5": { "trackUrl": "", "videoUrl": "", "planUrl": "" },
  "rs-2-3a": { "trackUrl": "", "videoUrl": "", "planUrl": "" },
  "rsp-m-2-3": { "trackUrl": "", "videoUrl": "", "planUrl": "" },
  "rs-2-4a": { "trackUrl": "", "videoUrl": "", "planUrl": "" },
  "rs-2-4b": { "trackUrl": "", "videoUrl": "", "planUrl": "" },
  "rsp-m-2-4": { "trackUrl": "", "videoUrl": "", "planUrl": "" },

  "tt-1-2a": { "trackUrl": "", "videoUrl": "", "planUrl": "" },
  "tt-1-2b": { "trackUrl": "", "videoUrl": "", "planUrl": "" },
  "ttv-1-2a": { "trackUrl": "", "videoUrl": "", "planUrl": "" },
  "ttp-m-1-2": { "trackUrl": "", "videoUrl": "", "planUrl": "" },
  "tt-1-3a": { "trackUrl": "", "videoUrl": "", "planUrl": "" },
  "tt-1-3b": { "trackUrl": "", "videoUrl": "", "planUrl": "" },
  "ttv-1-3a": { "trackUrl": "", "videoUrl": "", "planUrl": "" },
  "ttp-m-1-3": { "trackUrl": "", "videoUrl": "", "planUrl": "" },
  "tt-1-4a": { "trackUrl": "", "videoUrl": "", "planUrl": "" },
  "tt-1-4b": { "trackUrl": "", "videoUrl": "", "planUrl": "" },
  "ttp-m-1-4": { "trackUrl": "", "videoUrl": "", "planUrl": "" },
  "tt-2-2a": { "trackUrl": "", "videoUrl": "", "planUrl": "" },
  "ttp-m-2-2": { "trackUrl": "", "videoUrl": "", "planUrl": "" },
  "tt-2-3a": { "trackUrl": "", "videoUrl": "", "planUrl": "" },
  "tt-2-3b": { "trackUrl": "", "videoUrl": "", "planUrl": "" },
  "ttp-m-2-3": { "trackUrl": "", "videoUrl": "", "planUrl": "" },

  "jp-1-3a": { "trackUrl": "", "videoUrl": "", "planUrl": "" },
  "jpv-1-3a": { "trackUrl": "", "videoUrl": "", "planUrl": "" },
  "jpp-m-1-3": { "trackUrl": "", "videoUrl": "", "planUrl": "" },
  "jp-1-4a": { "trackUrl": "", "videoUrl": "", "planUrl": "" },
  "jpp-m-1-4": { "trackUrl": "", "videoUrl": "", "planUrl": "" },

  "ae-1-4a": { "trackUrl": "", "videoUrl": "", "planUrl": "" },
  "ae-1-4b": { "trackUrl": "", "videoUrl": "", "planUrl": "" },
  "aep-m-1-4": { "trackUrl": "", "videoUrl": "", "planUrl": "" },
  "ae-1-5a": { "trackUrl": "", "videoUrl": "", "planUrl": "" },
  "aev-1-5a": { "trackUrl": "", "videoUrl": "", "planUrl": "" },
  "aep-m-1-5": { "trackUrl": "", "videoUrl": "", "planUrl": "" },

  "mk-1-3a": { "trackUrl": "", "videoUrl": "", "planUrl": "" },
  "mkp-m-1-3": { "trackUrl": "", "videoUrl": "", "planUrl": "" },
  "mk-1-4a": { "trackUrl": "", "videoUrl": "", "planUrl": "" },
  "mkp-m-1-4": { "trackUrl": "", "videoUrl": "", "planUrl": "" },

  "at-1-4a": { "trackUrl": "", "videoUrl": "", "planUrl": "" },
  "atp-m-1-4": { "trackUrl": "", "videoUrl": "", "planUrl": "" },
  "at-1-5a": { "trackUrl": "", "videoUrl": "", "planUrl": "" },
  "atp-m-1-5": { "trackUrl": "", "videoUrl": "", "planUrl": "" },

  "pm-1-2a": { "trackUrl": "", "videoUrl": "", "planUrl": "" },
  "pm-1-2b": { "trackUrl": "", "videoUrl": "", "planUrl": "" },
  "pmv-1-2a": { "trackUrl": "", "videoUrl": "", "planUrl": "" },
  "pmp-m-1-2": { "trackUrl": "", "videoUrl": "", "planUrl": "" },
  "pm-1-3a": { "trackUrl": "", "videoUrl": "", "planUrl": "" },
  "pm-1-3b": { "trackUrl": "", "videoUrl": "", "planUrl": "" },
  "pmv-1-3a": { "trackUrl": "", "videoUrl": "", "planUrl": "" },
  "pmp-m-1-3": { "trackUrl": "", "videoUrl": "", "planUrl": "" },
  "pm-1-4a": { "trackUrl": "", "videoUrl": "", "planUrl": "" },
  "pm-1-4b": { "trackUrl": "", "videoUrl": "", "planUrl": "" },
  "pmp-m-1-4": { "trackUrl": "", "videoUrl": "", "planUrl": "" },

  "wm-1-3a": { "trackUrl": "", "videoUrl": "", "planUrl": "" },
  "wmv-1-3a": { "trackUrl": "", "videoUrl": "", "planUrl": "" },
  "wmp-m-1-3": { "trackUrl": "", "videoUrl": "", "planUrl": "" },
  "wm-1-4a": { "trackUrl": "", "videoUrl": "", "planUrl": "" },
  "wmp-m-1-4": { "trackUrl": "", "videoUrl": "", "planUrl": "" },
  "wm-1-5a": { "trackUrl": "", "videoUrl": "", "planUrl": "" },
  "wmp-m-1-5": { "trackUrl": "", "videoUrl": "", "planUrl": "" },

  "wmu-1-2a": { "trackUrl": "", "videoUrl": "", "planUrl": "" },
  "wmup-m-1-2": { "trackUrl": "", "videoUrl": "", "planUrl": "" },
  "wmu-1-3a": { "trackUrl": "", "videoUrl": "", "planUrl": "" },
  "wmup-m-1-3": { "trackUrl": "", "videoUrl": "", "planUrl": "" },

  "sc-1-2a": { "trackUrl": "", "videoUrl": "", "planUrl": "" },
  "sc-1-2b": { "trackUrl": "", "videoUrl": "", "planUrl": "" },
  "scp-m-1-2": { "trackUrl": "", "videoUrl": "", "planUrl": "" },
  "sc-1-3a": { "trackUrl": "", "videoUrl": "", "planUrl": "" },
  "scp-m-1-3": { "trackUrl": "", "videoUrl": "", "planUrl": "" },

  "fi-1-3a": { "trackUrl": "", "videoUrl": "", "planUrl": "" },
  "fip-m-1-3": { "trackUrl": "", "videoUrl": "", "planUrl": "" },
  "fi-1-4a": { "trackUrl": "", "videoUrl": "", "planUrl": "" },
  "fip-m-1-4": { "trackUrl": "", "videoUrl": "", "planUrl": "" },
  "fi-1-5a": { "trackUrl": "", "videoUrl": "", "planUrl": "" },
  "fip-m-1-5": { "trackUrl": "", "videoUrl": "", "planUrl": "" },

  "sf-1-3a": { "trackUrl": "", "videoUrl": "", "planUrl": "" },
  "sfp-m-1-3": { "trackUrl": "", "videoUrl": "", "planUrl": "" },
  "sf-1-4a": { "trackUrl": "", "videoUrl": "", "planUrl": "" },
  "sfp-m-1-4": { "trackUrl": "", "videoUrl": "", "planUrl": "" },

  "dd-1-4a": { "trackUrl": "", "videoUrl": "", "planUrl": "" },
  "ddv-1-4a": { "trackUrl": "", "videoUrl": "", "planUrl": "" },
  "ddp-m-1-4": { "trackUrl": "", "videoUrl": "", "planUrl": "" },
  "dd-1-5a": { "trackUrl": "", "videoUrl": "", "planUrl": "" },
  "ddp-m-1-5": { "trackUrl": "", "videoUrl": "", "planUrl": "" },

  "an-1-4a": { "trackUrl": "", "videoUrl": "", "planUrl": "" },
  "anp-m-1-4": { "trackUrl": "", "videoUrl": "", "planUrl": "" },

  "mg-1-3a": { "trackUrl": "", "videoUrl": "", "planUrl": "" },
  "mgp-m-1-3": { "trackUrl": "", "videoUrl": "", "planUrl": "" },
  "mg-1-4a": { "trackUrl": "", "videoUrl": "", "planUrl": "" },
  "mgp-m-1-4": { "trackUrl": "", "videoUrl": "", "planUrl": "" },

  "tg-1-4a": { "trackUrl": "", "videoUrl": "", "planUrl": "" },
  "tgp-m-1-4": { "trackUrl": "", "videoUrl": "", "planUrl": "" },
  "tg-1-5a": { "trackUrl": "", "videoUrl": "", "planUrl": "" },
  "tgp-m-1-5": { "trackUrl": "", "videoUrl": "", "planUrl": "" },

  "nr-1-3a": { "trackUrl": "", "videoUrl": "", "planUrl": "" },
  "nrp-m-1-3": { "trackUrl": "", "videoUrl": "", "planUrl": "" },
  "nr-1-4a": { "trackUrl": "", "videoUrl": "", "planUrl": "" },
  "nrp-m-1-4": { "trackUrl": "", "videoUrl": "", "planUrl": "" },

  "a-1-2a":  { "trackUrl": "", "videoUrl": "", "planUrl": "" },
  "pa-m-1-2":{ "trackUrl": "", "videoUrl": "", "planUrl": "" },
  "a-1-3a":  { "trackUrl": "", "videoUrl": "", "planUrl": "" },
  "pa-m-1-3":{ "trackUrl": "", "videoUrl": "", "planUrl": "" },
  "a-1-4a":  { "trackUrl": "", "videoUrl": "", "planUrl": "" },
  "pa-m-1-4":{ "trackUrl": "", "videoUrl": "", "planUrl": "" },

  "r-1-3a":  { "trackUrl": "", "videoUrl": "", "planUrl": "" },
  "pr-m-1-3":{ "trackUrl": "", "videoUrl": "", "planUrl": "" },
  "r-1-4a":  { "trackUrl": "", "videoUrl": "", "planUrl": "" },
  "pr-m-1-4":{ "trackUrl": "", "videoUrl": "", "planUrl": "" },

  "mt-1-3a":  { "trackUrl": "", "videoUrl": "", "planUrl": "" },
  "pmt-m-1-3":{ "trackUrl": "", "videoUrl": "", "planUrl": "" },
  "mt-1-4a":  { "trackUrl": "", "videoUrl": "", "planUrl": "" },
  "pmt-m-1-4":{ "trackUrl": "", "videoUrl": "", "planUrl": "" },

  "h-1-3a":  { "trackUrl": "", "videoUrl": "", "planUrl": "" },
  "ph-m-1-3":{ "trackUrl": "", "videoUrl": "", "planUrl": "" },
  "h-1-4a":  { "trackUrl": "", "videoUrl": "", "planUrl": "" },
  "ph-m-1-4":{ "trackUrl": "", "videoUrl": "", "planUrl": "" },
  "h-1-5a":  { "trackUrl": "", "videoUrl": "", "planUrl": "" },
  "ph-m-1-5":{ "trackUrl": "", "videoUrl": "", "planUrl": "" },

  "evt-ca-1": { "trackUrl": "", "videoUrl": "", "planUrl": "" },
  "evt-ca-2": { "trackUrl": "", "videoUrl": "", "planUrl": "" },
  "evv-ca-1": { "trackUrl": "", "videoUrl": "", "planUrl": "" },
  "evp-ca-1": { "trackUrl": "", "videoUrl": "", "planUrl": "" },
  "evt-ny-1": { "trackUrl": "", "videoUrl": "", "planUrl": "" },
  "evv-ny-1": { "trackUrl": "", "videoUrl": "", "planUrl": "" },
  "evp-ny-1": { "trackUrl": "", "videoUrl": "", "planUrl": "" },
  "evt-tx-1": { "trackUrl": "", "videoUrl": "", "planUrl": "" },
  "evp-tx-1": { "trackUrl": "", "videoUrl": "", "planUrl": "" },
  "evt-hi-1": { "trackUrl": "", "videoUrl": "", "planUrl": "" },
  "evt-hi-2": { "trackUrl": "", "videoUrl": "", "planUrl": "" },
  "evv-hi-1": { "trackUrl": "", "videoUrl": "", "planUrl": "" },
  "evp-hi-1": { "trackUrl": "", "videoUrl": "", "planUrl": "" },
  "evt-fl-1": { "trackUrl": "", "videoUrl": "", "planUrl": "" },
  "evp-fl-1": { "trackUrl": "", "videoUrl": "", "planUrl": "" },
  "evt-ak-1": { "trackUrl": "", "videoUrl": "", "planUrl": "" },
  "evv-ak-1": { "trackUrl": "", "videoUrl": "", "planUrl": "" },
  "evp-ak-1": { "trackUrl": "", "videoUrl": "", "planUrl": "" },
  "evt-il-1": { "trackUrl": "", "videoUrl": "", "planUrl": "" },
  "evp-il-1": { "trackUrl": "", "videoUrl": "", "planUrl": "" },
  "evt-co-1": { "trackUrl": "", "videoUrl": "", "planUrl": "" },
  "evp-co-1": { "trackUrl": "", "videoUrl": "", "planUrl": "" },
  "evt-la-1": { "trackUrl": "", "videoUrl": "", "planUrl": "" },
  "evv-la-1": { "trackUrl": "", "videoUrl": "", "planUrl": "" },
  "evp-la-1": { "trackUrl": "", "videoUrl": "", "planUrl": "" },
  "evt-dc-1": { "trackUrl": "", "videoUrl": "", "planUrl": "" },
  "evp-dc-1": { "trackUrl": "", "videoUrl": "", "planUrl": "" },
  "evt-az-1": { "trackUrl": "", "videoUrl": "", "planUrl": "" },
  "evp-az-1": { "trackUrl": "", "videoUrl": "", "planUrl": "" },
  "evt-ma-1": { "trackUrl": "", "videoUrl": "", "planUrl": "" },
  "evp-ma-1": { "trackUrl": "", "videoUrl": "", "planUrl": "" },
  "evt-ph-1": { "trackUrl": "", "videoUrl": "", "planUrl": "" },
  "evv-ph-1": { "trackUrl": "", "videoUrl": "", "planUrl": "" },
  "evp-ph-1": { "trackUrl": "", "videoUrl": "", "planUrl": "" },
  "evt-rb-1": { "trackUrl": "", "videoUrl": "", "planUrl": "" },
  "evv-rb-1": { "trackUrl": "", "videoUrl": "", "planUrl": "" },
  "evp-rb-1": { "trackUrl": "", "videoUrl": "", "planUrl": "" },
  "evt-bm-1": { "trackUrl": "", "videoUrl": "", "planUrl": "" },
  "evt-bm-2": { "trackUrl": "", "videoUrl": "", "planUrl": "" },
  "evt-bm-3": { "trackUrl": "", "videoUrl": "", "planUrl": "" },
  "evv-bm-1": { "trackUrl": "", "videoUrl": "", "planUrl": "" },
  "evp-bm-1": { "trackUrl": "", "videoUrl": "", "planUrl": "" },
  "evp-bm-2": { "trackUrl": "", "videoUrl": "", "planUrl": "" },
  "evt-pn-1": { "trackUrl": "", "videoUrl": "", "planUrl": "" },
  "evp-pn-1": { "trackUrl": "", "videoUrl": "", "planUrl": "" },
  "evt-sc-1": { "trackUrl": "", "videoUrl": "", "planUrl": "" },
  "evv-sc-1": { "trackUrl": "", "videoUrl": "", "planUrl": "" },
  "evp-sc-1": { "trackUrl": "", "videoUrl": "", "planUrl": "" }
}
